itk/FastBilateralPython.py
itk/_FastBilateralPython.pyd
itk/__init_fastbilateral__.py
itk/itkFastBilateralImageFilterPython.py
itk/Configuration/FastBilateralConfig.py
itk/Configuration/FastBilateral_snake_case.py
itk_fastbilateral-1.0.1.dist-info/licenses/LICENSE
itk_fastbilateral.libs/msvcp140.dll
itk_fastbilateral.libs/tbb12.dll
itk_fastbilateral-1.0.1.dist-info/DELVEWHEEL
itk_fastbilateral-1.0.1.dist-info/METADATA
itk_fastbilateral-1.0.1.dist-info/WHEEL
itk_fastbilateral-1.0.1.dist-info/RECORD
